odre.py
odre-0.9.7.dist-info/LICENSE
odre-0.9.7.dist-info/METADATA
odre-0.9.7.dist-info/WHEEL
odre-0.9.7.dist-info/top_level.txt
odre-0.9.7.dist-info/RECORD
