Metadata-Version: 2.1
Name: odre
Version: 0.9.7
Summary: Bottle extension for user authentication based on pgusers
Home-page: https://github.com/destrangis/odre
Author: Javier Llopis
Author-email: javier@llopis.me
License: MIT
Classifier: Development Status :: 4 - Beta
Classifier: Framework :: Bottle
Classifier: Intended Audience :: Developers
Classifier: License :: OSI Approved :: MIT License
Classifier: Operating System :: OS Independent
Classifier: Programming Language :: Python :: 3 :: Only
Classifier: Topic :: Internet :: WWW/HTTP :: WSGI :: Middleware
Classifier: Topic :: Software Development :: Libraries :: Python Modules
License-File: LICENSE
Requires-Dist: bottle
Requires-Dist: pgusers
